Constellation_DeviceManager-0.1.3.dist-info/DESCRIPTION.rst
Constellation_DeviceManager-0.1.3.dist-info/METADATA
Constellation_DeviceManager-0.1.3.dist-info/RECORD
Constellation_DeviceManager-0.1.3.dist-info/WHEEL
Constellation_DeviceManager-0.1.3.dist-info/metadata.json
Constellation_DeviceManager-0.1.3.dist-info/top_level.txt
constellation_devicemanager/__init__.py
constellation_devicemanager/admin.py
constellation_devicemanager/apps.py
constellation_devicemanager/forms.py
constellation_devicemanager/models.py
constellation_devicemanager/urls.py
constellation_devicemanager/validators.py
constellation_devicemanager/views.py
constellation_devicemanager/migrations/0001_initial.py
constellation_devicemanager/migrations/0002_device_hostname.py
constellation_devicemanager/migrations/__init__.py
constellation_devicemanager/static/constellation_devicemanager/js/view-list.js
constellation_devicemanager/templates/constellation_devicemanager/dashboard.html
constellation_devicemanager/templates/constellation_devicemanager/view-list.html
